{
    "users": [
        {
            "password": "1234",
            "isAdmin": false,
            "email": "s.noren89@gmail.com",
            "name": "Sebastian Norén",
            "professionLabel": "Software Enginner",
            "age": 31,
            "country": "Sweden",
            "yearsExperience": 2,
            "pricePerHour": 200,
            "selfDescription": "King",
            "isBanned": false,
            "skillset": [{ "skillName": "Java", "skillRate": 5 }]
        },
        {
            "password": "hejhej123",
            "isAdmin": false,
            "email": "hithereman@gmail.com",
            "name": "Gunnar Alibaba",
            "professionLabel": "desktop-master",
            "age": 26,
            "country": "Iraq",
            "yearsExperience": 4,
            "pricePerHour": 35,
            "selfDescription": "kinda cool",
            "isBanned": false,
            "skillset": [{ "skillName": "Java", "skillRate": 5 }]
        },
        {
            "password": "1234",
            "isAdmin": false,
            "email": "liedra@optonline.net",
            "name": "Ashley Williams",
            "professionLabel": "desktop-master",
            "age": 21,
            "country": "England",
            "yearsExperience": 4,
            "pricePerHour": 35,
            "selfDescription": "kinda cool",
            "isBanned": false,
            "skillset": [{ "skillName": "Java", "skillRate": 5 }]
        },
        {
            "password": "1234",
            "isAdmin": false,
            "email": "phyruxus@live.com",
            "name": "Kygo Machimada",
            "professionLabel": "desktop-master",
            "age": 18,
            "country": "Japan",
            "yearsExperience": 1,
            "pricePerHour": 10,
            "selfDescription": "kinda cool",
            "isBanned": false,
            "skillset": [{ "skillName": "Java", "skillRate": 5 }]
        },
        {
            "password": "1234",
            "isAdmin": false,
            "email": "cparis@sbcglobal.net",
            "name": "Halvdan sörrensen",
            "professionLabel": "desktop-master",
            "age": 55,
            "country": "Denmark",
            "yearsExperience": 4,
            "pricePerHour": 35,
            "selfDescription": "kinda cool",
            "isBanned": false,
            "skillset": [{ "skillName": "Java", "skillRate": 5 }]
        },
        {
            "password": "1234",
            "isAdmin": false,
            "email": "ghaviv@gmail.com",
            "name": "Sten-Sture Svensson",
            "professionLabel": "desktop-master",
            "age": 24,
            "country": "Sweden",
            "yearsExperience": 4,
            "pricePerHour": 35,
            "selfDescription": "kinda cool",
            "isBanned": false,
            "skillset": [{ "skillName": "Java", "skillRate": 5 }]
        },
        {
            "password": "1234",
            "isAdmin": false,
            "email": "folke@gmail.com",
            "name": "Mark Adams",
            "professionLabel": "desktop-master",
            "age": 28,
            "country": "USA",
            "yearsExperience": 4,
            "pricePerHour": 35,
            "selfDescription": "kinda cool",
            "isBanned": false,
            "skillset": [{ "skillName": "Java", "skillRate": 5 }]
        }]
  } 